django_referer_csrf/__init__.py
django_referer_csrf/tests/__init__.py
django_referer_csrf/tests/tests.py
django_referer_csrf/tests/urls.py
django_referer_csrf-0.2.0.dist-info/LICENSE
django_referer_csrf-0.2.0.dist-info/METADATA
django_referer_csrf-0.2.0.dist-info/WHEEL
django_referer_csrf-0.2.0.dist-info/top_level.txt
django_referer_csrf-0.2.0.dist-info/RECORD
