Metadata-Version: 2.1
Name: django-referer-csrf
Version: 0.2.0
Summary: TODO
Home-page: https://github.com/quadrant-newmedia/django_referer_csrf
Author: Alex Fischer
Author-email: alex@quadrant.net
License: UNKNOWN
Platform: UNKNOWN
Classifier: Programming Language :: Python :: 3
Classifier: License :: OSI Approved :: MIT License
Classifier: Operating System :: OS Independent
Requires-Python: >=3.7
Requires-Dist: Django (<6,>=3)
